FunctionTraceHTML/FunctionTrace.py
FunctionTraceHTML/__init__.py
functiontracehtml-1.1.dist-info/licenses/LICENSE
functiontracehtml-1.1.dist-info/METADATA
functiontracehtml-1.1.dist-info/WHEEL
functiontracehtml-1.1.dist-info/top_level.txt
functiontracehtml-1.1.dist-info/RECORD
