Metadata-Version: 2.4
Name: FunctionTraceHTML
Version: 1.1
Summary: Trace Python functions into a color coded HTML log file.
Author: charlie-de-muis
License-Expression: MIT
Project-URL: Homepage, https://github.com/charlie-de-muis/FunctionTraceHTML
Classifier: Programming Language :: Python :: 3
Classifier: Operating System :: OS Independent
Requires-Python: >=3.9
License-File: LICENSE
Dynamic: license-file
